{
    "classes": [
        {
            "className": "RunwayManager",
            "object": true,
            "properties": [
                {
                    "constant": true,
                    "designable": true,
                    "final": false,
                    "index": 0,
                    "name": "runway1Occupied",
                    "read": "runway1Occupied",
                    "required": false,
                    "scriptable": true,
                    "stored": true,
                    "type": "bool",
                    "user": false
                },
                {
                    "constant": true,
                    "designable": true,
                    "final": false,
                    "index": 1,
                    "name": "runway2Occupied",
                    "read": "runway2Occupied",
                    "required": false,
                    "scriptable": true,
                    "stored": true,
                    "type": "bool",
                    "user": false
                },
                {
                    "constant": true,
                    "designable": true,
                    "final": false,
                    "index": 2,
                    "name": "runway3Occupied",
                    "read": "runway3Occupied",
                    "required": false,
                    "scriptable": true,
                    "stored": true,
                    "type": "bool",
                    "user": false
                }
            ],
            "qualifiedClassName": "RunwayManager",
            "superClasses": [
                {
                    "access": "public",
                    "name": "QObject"
                }
            ]
        }
    ],
    "inputFile": "runwaymanager.h",
    "outputRevision": 68
}
